pkgconfig/__init__.py
pkgconfig/pkgconfig.py
pkgconfig-1.5.4.dist-info/LICENSE
pkgconfig-1.5.4.dist-info/WHEEL
pkgconfig-1.5.4.dist-info/METADATA
pkgconfig-1.5.4.dist-info/RECORD
