Metadata-Version: 2.1
Name: pkgconfig
Version: 1.5.4
Summary: Interface Python with pkg-config
Home-page: https://github.com/matze/pkgconfig
License: MIT
Author: Matthias Vogelgesang
Author-email: matthias.vogelgesang@gmail.com
Requires-Python: >=3.3,<4.0
Classifier: Development Status :: 5 - Production/Stable
Classifier: Intended Audience :: Developers
Classifier: License :: OSI Approved :: MIT License
Classifier: Operating System :: OS Independent
Classifier: Programming Language :: Python :: 3
Classifier: Programming Language :: Python :: 3.4
Classifier: Programming Language :: Python :: 3.5
Classifier: Programming Language :: Python :: 3.6
Classifier: Programming Language :: Python :: 3.7
Classifier: Programming Language :: Python :: 3.8
Classifier: Programming Language :: Python :: 3.9
Classifier: Topic :: Software Development :: Build Tools
